fbs/__init__.py
fbs/__main__.py
fbs/_aws.py
fbs/_gpg.py
fbs/_server.py
fbs/_state.py
fbs/cmdline.py
fbs/resources.py
fbs/upload.py
fbs/_defaults/requirements/arch.txt
fbs/_defaults/requirements/base.txt
fbs/_defaults/requirements/fedora.txt
fbs/_defaults/requirements/linux.txt
fbs/_defaults/requirements/ubuntu.txt
fbs/_defaults/src/build/docker/arch/.bashrc
fbs/_defaults/src/build/docker/arch/Dockerfile
fbs/_defaults/src/build/docker/arch/gpg-agent.conf
fbs/_defaults/src/build/docker/arch/motd
fbs/_defaults/src/build/docker/fedora/.bashrc
fbs/_defaults/src/build/docker/fedora/.rpmmacros
fbs/_defaults/src/build/docker/fedora/Dockerfile
fbs/_defaults/src/build/docker/fedora/gpg-agent.conf
fbs/_defaults/src/build/docker/fedora/motd
fbs/_defaults/src/build/docker/ubuntu/.bashrc
fbs/_defaults/src/build/docker/ubuntu/Dockerfile
fbs/_defaults/src/build/docker/ubuntu/gpg-agent.conf
fbs/_defaults/src/build/docker/ubuntu/gpg.conf
fbs/_defaults/src/build/docker/ubuntu/motd
fbs/_defaults/src/build/settings/arch.json
fbs/_defaults/src/build/settings/base.json
fbs/_defaults/src/build/settings/fedora.json
fbs/_defaults/src/build/settings/linux.json
fbs/_defaults/src/build/settings/mac.json
fbs/_defaults/src/build/settings/release.json
fbs/_defaults/src/build/settings/ubuntu.json
fbs/_defaults/src/build/settings/windows.json
fbs/_defaults/src/freeze/mac/Contents/Info.plist
fbs/_defaults/src/freeze/windows/version_info.py
fbs/_defaults/src/installer/linux/usr/share/applications/AppName.desktop
fbs/_defaults/src/installer/windows/Installer.nsi
fbs/_defaults/src/repo/fedora/AppName.repo
fbs/_defaults/src/repo/ubuntu/distributions
fbs/builtin_commands/__init__.py
fbs/builtin_commands/_account.py
fbs/builtin_commands/_docker.py
fbs/builtin_commands/_licensing.py
fbs/builtin_commands/_util.py
fbs/builtin_commands/_gpg/Dockerfile
fbs/builtin_commands/_gpg/__init__.py
fbs/builtin_commands/_gpg/genkey.sh
fbs/builtin_commands/_gpg/gpg-agent.conf
neofbs-1.2.6.dist-info/LICENSE
neofbs-1.2.6.dist-info/METADATA
neofbs-1.2.6.dist-info/NOTICE
neofbs-1.2.6.dist-info/WHEEL
neofbs-1.2.6.dist-info/entry_points.txt
neofbs-1.2.6.dist-info/top_level.txt
neofbs-1.2.6.dist-info/RECORD
